felis/__init__.py
felis/applicative.py
felis/bool.py
felis/coroutine.py
felis/coroutine_option.py
felis/currying.py
felis/dict.py
felis/either.py
felis/either_t.py
felis/free.py
felis/free_dict.py
felis/free_t.py
felis/function_option.py
felis/identity.py
felis/iterable.py
felis/lazy.py
felis/lazy_coroutine.py
felis/lazy_coroutine_either.py
felis/lazy_coroutine_either_list.py
felis/lazy_coroutine_option.py
felis/lazy_t.py
felis/list.py
felis/list_t.py
felis/monad.py
felis/option.py
felis/option_t.py
felis/order.py
felis/ordering.py
felis/pair.py
felis/parser.py
felis/py.typed
felis/state.py
felis/state_t.py
felis/typing.py
felis/constrained/__init__.py
felis/constrained/float.py
felis/constrained/int.py
felis/constrained/str.py
felis/function/__init__.py
felis/function/flip_.py
felis/function/identity_.py
felis/predicate/__init__.py
felis/predicate/bool.py
felis/predicate/comparison.py
felis/predicate/float.py
felis/predicate/interval.py
felis_catus-0.dev5.dist-info/LICENSE
felis_catus-0.dev5.dist-info/METADATA
felis_catus-0.dev5.dist-info/WHEEL
felis_catus-0.dev5.dist-info/top_level.txt
felis_catus-0.dev5.dist-info/RECORD
