Metadata-Version: 2.2
Name: felis-catus
Version: 0.dev5
Summary: 🐈 Felis Catus – functional bits for Python
Author-email: LeeeeT <me@LeeeeT.dev>
License: Permission to use, copy, modify, and/or distribute this software for any
Project-URL: Homepage, https://github.com/LeeeeT/felis
Project-URL: Documentation, https://felis.LeeeeT.dev
Project-URL: Repository, https://github.com/LeeeeT/felis
Project-URL: PyPI, https://pypi.org/project/felis-catus
Classifier: Intended Audience :: Developers
Classifier: Intended Audience :: Information Technology
Classifier: License :: OSI Approved :: Zero-Clause BSD (0BSD)
Classifier: Operating System :: OS Independent
Classifier: Programming Language :: Python
Classifier: Programming Language :: Python :: 3
Classifier: Programming Language :: Python :: 3 :: Only
Classifier: Programming Language :: Python :: 3.12
Classifier: Topic :: Software Development :: Libraries
Classifier: Topic :: Software Development :: Libraries :: Python Modules
Classifier: Typing :: Typed
Requires-Python: >=3.12
License-File: LICENSE
